miracle/__init__.py
miracle/acl.py
miracle_acl-0.0.4_1.dist-info/metadata.json
miracle_acl-0.0.4_1.dist-info/RECORD
miracle_acl-0.0.4_1.dist-info/top_level.txt
miracle_acl-0.0.4_1.dist-info/DESCRIPTION.rst
miracle_acl-0.0.4_1.dist-info/WHEEL
miracle_acl-0.0.4_1.dist-info/METADATA
