Metadata-Version: 2.0
Name: miracle-acl
Version: 0.0.4-1
Summary: Flexible role-based authorization solution that is a pleasure to use
Home-page: https://github.com/kolypto/py-miracle
Author: Mark Vartanyan
Author-email: kolypto@gmail.com
License: MIT
Keywords: acl,rbac,authorization
Platform: any
Classifier: Development Status :: 5 - Production/Stable
Classifier: Intended Audience :: Developers
Classifier: Natural Language :: English
Classifier: Programming Language :: Python :: 2
Classifier: Programming Language :: Python :: 3
Classifier: Operating System :: OS Independent
Provides-Extra: _dev
Requires-Dist: wheel; extra == '_dev'
Requires-Dist: nose; extra == '_dev'
